Metadata-Version: 2.1
Name: odoo12-addon-stock-archive-constraint
Version: 12.0.1.0.2
Summary: Stock archive constraint
Home-page: https://github.com/OCA/stock-logistics-warehouse
Author: Tecnativa, Odoo Community Association (OCA)
Author-email: support@odoo-community.org
License: AGPL-3
Platform: UNKNOWN
Classifier: Programming Language :: Python
Classifier: Framework :: Odoo
Classifier: Framework :: Odoo :: 12.0
Classifier: License :: OSI Approved :: GNU Affero General Public License v3
Classifier: Development Status :: 5 - Production/Stable
Requires-Python: >=3.5
Requires-Dist: odoo (<12.1dev,>=12.0a)
